{
    "header": {
        "version": "1.0",
        "app": "iis setup"
    },
    "project": {
        "name": "New Project"
    },
    "client_authority": {
        "common_name": "Meine Test CA",
        "organisation": "My Company Big Fail",
        "organisation_unit": "IT",
        "location": "Erfurt",
        "country": "DE",
        "algorithm": "RSA",
        "key_size": "4096",
        "not_before": "2026-05-02",
        "not_after": "2036-05-04",
        "basic_constraints": true,
        "usage": "trusted_ca",
        "store": "personal",
        "scope": "current_user"
    },
    "client_certs": []
}